__main__.py
zipimport_ext.py
magicmain-0.3.1.dist-info/METADATA
magicmain-0.3.1.dist-info/WHEEL
magicmain-0.3.1.dist-info/top_level.txt
magicmain-0.3.1.dist-info/RECORD
