Metadata-Version: 2.1
Name: magicmain
Version: 0.3.1
Summary: Make appendable dependency zips
Home-page: http://github.com/orent/magicmain
Author: Oren Tirosh
Author-email: orent@hishome.net
Requires-Python: >=2.7
